README.md
setup.py
alphanym/__init__.py
alphanym.egg-info/PKG-INFO
alphanym.egg-info/SOURCES.txt
alphanym.egg-info/dependency_links.txt
alphanym.egg-info/not-zip-safe
alphanym.egg-info/requires.txt
alphanym.egg-info/top_level.txt