Metadata-Version: 1.0
Name: alphanym
Version: 1.0.2
Summary: Official Alphanym Python Client
Home-page: https://www.alphanym.com
Author: Drew French
Author-email: french@alphanym.com
License: MIT License
Keywords: Alphanym
Platform: UNKNOWN
